{"format": "kyra-scene-meta", "scene": "GENCAVB", "drawLayerTable": [47, 47, 44, 97, 0, 0, 0, 136], "spriteDefs": [{"id": 0, "x": 8, "y": 139, "w": 24, "h": 53}, {"id": 1, "x": 32, "y": 139, "w": 40, "h": 14}, {"id": 2, "x": 32, "y": 153, "w": 32, "h": 35}, {"id": 3, "x": 72, "y": 139, "w": 56, "h": 29}], "anims": [{"disable": true, "unk2": 0, "drawY": 0, "defaultX": 160, "defaultY": 21, "width": 21, "height": 4, "sprite": 2, "flipX": true, "width2": 1, "height2": 0, "unk1": false, "play": false, "script": [65419, 65415]}, {"disable": true, "unk2": 0, "drawY": 0, "defaultX": 266, "defaultY": 45, "width": 45, "height": 3, "sprite": 0, "flipX": true, "width2": 1, "height2": 0, "unk1": false, "play": false, "script": [65419, 65415]}, {"disable": false, "unk2": 0, "drawY": 136, "defaultX": 114, "defaultY": 122, "width": 122, "height": 5, "sprite": 1, "flipX": true, "width2": 1, "height2": 0, "unk1": false, "play": false, "script": [65419, 65415]}, {"disable": true, "unk2": 0, "drawY": 0, "defaultX": 38, "defaultY": 48, "width": 48, "height": 3, "sprite": 0, "flipX": false, "width2": 0, "height2": 0, "unk1": false, "play": false, "script": [65419, 65415]}, {"disable": false, "unk2": 0, "drawY": 93, "defaultX": 136, "defaultY": 71, "width": 71, "height": 3, "sprite": 3, "flipX": true, "width2": 1, "height2": 0, "unk1": false, "play": false, "script": [65419, 65415]}]}